bregman/__init__.py
bregman/base.py
bregman/constants.py
bregman/application/__init__.py
bregman/application/application.py
bregman/application/distribution/__init__.py
bregman/application/distribution/distribution.py
bregman/application/distribution/exponential_family/__init__.py
bregman/application/distribution/exponential_family/exp_family.py
bregman/application/distribution/exponential_family/categorical/__init__.py
bregman/application/distribution/exponential_family/categorical/categorical.py
bregman/application/distribution/exponential_family/gaussian/__init__.py
bregman/application/distribution/exponential_family/gaussian/dissimilarity.py
bregman/application/distribution/exponential_family/gaussian/gaussian.py
bregman/application/distribution/exponential_family/gaussian/geodesic.py
bregman/application/distribution/exponential_family/multinomial/__init__.py
bregman/application/distribution/exponential_family/multinomial/dissimilarity.py
bregman/application/distribution/exponential_family/multinomial/geodesic.py
bregman/application/distribution/exponential_family/multinomial/multinomial.py
bregman/application/distribution/mixture/__init__.py
bregman/application/distribution/mixture/mixture.py
bregman/application/distribution/mixture/discrete_mixture/__init__.py
bregman/application/distribution/mixture/discrete_mixture/discrete_mixture.py
bregman/application/distribution/mixture/ef_mixture/__init__.py
bregman/application/distribution/mixture/ef_mixture/ef_mixture.py
bregman/application/psd/__init__.py
bregman/application/psd/psd.py
bregman/ball/__init__.py
bregman/ball/base.py
bregman/ball/bregman.py
bregman/ball/parameterized.py
bregman/barycenter/__init__.py
bregman/barycenter/base.py
bregman/barycenter/bregman.py
bregman/dissimilarity/__init__.py
bregman/dissimilarity/base.py
bregman/dissimilarity/bregman.py
bregman/manifold/__init__.py
bregman/manifold/bisector.py
bregman/manifold/connection.py
bregman/manifold/coordinate.py
bregman/manifold/generator.py
pybregman-0.1.1.dist-info/licenses/LICENSE
pybregman-0.1.1.dist-info/METADATA
pybregman-0.1.1.dist-info/WHEEL
pybregman-0.1.1.dist-info/top_level.txt
pybregman-0.1.1.dist-info/RECORD
