Metadata-Version: 2.4
Name: pyBregMan
Version: 0.1.1
Summary: A Python library for geometric computing on BREGman MANifolds with applications.
Author-email: alexandersoen <alexandersoen@gmail.com>
License: 
Project-URL: Homepage, https://franknielsen.github.io/pyBregMan/index.html
Project-URL: Documentation, https://pybregman.readthedocs.io/en/latest
Project-URL: Repository, https://github.com/alexandersoen/pyBregMan
Project-URL: Issues, https://github.com/alexandersoen/pyBregMan/issues
Classifier: Programming Language :: Python :: 3
Classifier: Development Status :: 3 - Alpha
Classifier: License :: OSI Approved :: Apache Software License
Classifier: Operating System :: OS Independent
Classifier: Topic :: Scientific/Engineering :: Mathematics
Requires-Python: >=3.8
License-File: LICENSE
Requires-Dist: numpy<2.0.0
Requires-Dist: matplotlib
Requires-Dist: scipy
Requires-Dist: autograd
Dynamic: license-file
